external_vision_gateway_adapter/__init__.py
external_vision_gateway_adapter/base_adapter.py
external_vision_gateway_adapter/server_client_adapter.py
resources/__init__.py
resources/grpc/__init__.py
resources/grpc/server_proto/__init__.py
resources/grpc/server_proto/external_tool_service.proto
resources/grpc/server_proto/external_tool_service_pb2.py
resources/grpc/server_proto/external_tool_service_pb2_grpc.py
tests/__init__.py
tests/adapter_client_test.py
external_vision_gateway_adapter_package-0.1.5.dist-info/METADATA
external_vision_gateway_adapter_package-0.1.5.dist-info/WHEEL
external_vision_gateway_adapter_package-0.1.5.dist-info/top_level.txt
external_vision_gateway_adapter_package-0.1.5.dist-info/RECORD
