Metadata-Version: 2.4
Name: external-vision-gateway-adapter-package
Version: 0.1.5
Summary: Gateway Adapter to be used by clients to communicate with the gateway service.
Author: Ugenteraan
Author-email: ugen@evlos.ai
Classifier: Programming Language :: Python :: 3
Classifier: License :: OSI Approved :: MIT License
Classifier: Operating System :: OS Independent
Requires-Python: >=3.9
Requires-Dist: grpcio
Requires-Dist: grpcio-tools
Requires-Dist: protobuf
Dynamic: author
Dynamic: author-email
Dynamic: classifier
Dynamic: requires-dist
Dynamic: requires-python
Dynamic: summary
